{
  "PRESENTE": {
    "YO": {
      "SPANISH": "Cumplo",
      "ENGLISH": "I carry out"
    },
    "TU": {
      "SPANISH": "Cumples",
      "ENGLISH": "You carry out"
    },
    "EL": {
      "SPANISH": "Cumple",
      "ENGLISH": "He carries out"
    },
    "ELLOS": {
      "SPANISH": "Cumplen",
      "ENGLISH": "They carry out"
    },
    "NOSOTROS": {
      "SPANISH": "Cumplimos",
      "ENGLISH": "We carry out"
    },
    "VOSOTROS": {
      "SPANISH": "Cumplís",
      "ENGLISH": "You carry out"
    }
  },
  "PERFECTO_COMPUESTO": {
    "YO": {
      "SPANISH": "He cumplido",
      "ENGLISH": "I have carried out"
    },
    "TU": {
      "SPANISH": "Has cumplido",
      "ENGLISH": "You have carried out"
    },
    "EL": {
      "SPANISH": "Ha cumplido",
      "ENGLISH": "He has carried out"
    },
    "ELLOS": {
      "SPANISH": "Han cumplido",
      "ENGLISH": "They have carried out"
    },
    "NOSOTROS": {
      "SPANISH": "Hemos cumplido",
      "ENGLISH": "We have carried out"
    },
    "VOSOTROS": {
      "SPANISH": "Habéis cumplido",
      "ENGLISH": "You have carried out"
    }
  },
  "PRETERITO_INDEFINIDO": {
    "YO": {
      "SPANISH": "Cumplí",
      "ENGLISH": "I carried out"
    },
    "TU": {
      "SPANISH": "Cumpliste",
      "ENGLISH": "You carried out"
    },
    "EL": {
      "SPANISH": "Cumplió",
      "ENGLISH": "He carried out"
    },
    "ELLOS": {
      "SPANISH": "Cumplieron",
      "ENGLISH": "They carried out"
    },
    "NOSOTROS": {
      "SPANISH": "Cumplimos",
      "ENGLISH": "We carried out"
    },
    "VOSOTROS": {
      "SPANISH": "Cumplisteis",
      "ENGLISH": "You carried out"
    }
  },
  "PRETERITO_PLUSCUAMPERFECTO": {
    "YO": {
      "SPANISH": "Había cumplido",
      "ENGLISH": "I had carried out"
    },
    "TU": {
      "SPANISH": "Habías cumplido",
      "ENGLISH": "You had carried out"
    },
    "EL": {
      "SPANISH": "Había cumplido",
      "ENGLISH": "He had carried out"
    },
    "ELLOS": {
      "SPANISH": "Habían cumplido",
      "ENGLISH": "They had carried out"
    },
    "NOSOTROS": {
      "SPANISH": "Habíamos cumplido",
      "ENGLISH": "We had carried out"
    },
    "VOSOTROS": {
      "SPANISH": "Habíais cumplido",
      "ENGLISH": "You had carried out"
    }
  },
  "PRETERITO_IMPERFECTO": {
    "YO": {
      "SPANISH": "Cumplí",
      "ENGLISH": "I carried out"
    },
    "TU": {
      "SPANISH": "Cumpliste",
      "ENGLISH": "You carried out"
    },
    "EL": {
      "SPANISH": "Cumplió",
      "ENGLISH": "He carried out"
    },
    "ELLOS": {
      "SPANISH": "Cumplieron",
      "ENGLISH": "They carried out"
    },
    "NOSOTROS": {
      "SPANISH": "Cumplimos",
      "ENGLISH": "We carried out"
    },
    "VOSOTROS": {
      "SPANISH": "Cumplisteis",
      "ENGLISH": "You carried out"
    }
  },
  "FUTURO_SIMPLE": {
    "YO": {
      "SPANISH": "Cumpliré",
      "ENGLISH": "I will carry out"
    },
    "TU": {
      "SPANISH": "Cumplirás",
      "ENGLISH": "You will carry out"
    },
    "EL": {
      "SPANISH": "Cumplirá",
      "ENGLISH": "He will carry out"
    },
    "ELLOS": {
      "SPANISH": "Cumplirán",
      "ENGLISH": "They will carry out"
    },
    "NOSOTROS": {
      "SPANISH": "Cumpliremos",
      "ENGLISH": "We will carry out"
    },
    "VOSOTROS": {
      "SPANISH": "Cumpliréis",
      "ENGLISH": "You will carry out"
    }
  },
  "FUTURO_COMPUESTO": {
    "YO": {
      "SPANISH": "Habré cumplido",
      "ENGLISH": "I will have carried out"
    },
    "TU": {
      "SPANISH": "Habrás cumplido",
      "ENGLISH": "You will have carried out"
    },
    "EL": {
      "SPANISH": "Habrá cumplido",
      "ENGLISH": "He will have carried out"
    },
    "ELLOS": {
      "SPANISH": "Habrán cumplido",
      "ENGLISH": "They will have carried out"
    },
    "NOSOTROS": {
      "SPANISH": "Habremos cumplido",
      "ENGLISH": "We will have carried out"
    },
    "VOSOTROS": {
      "SPANISH": "Habréis cumplido",
      "ENGLISH": "You will have carried out"
    }
  },
  "CONDICIONAL_SIMPLE": {
    "YO": {
      "SPANISH": "Cumpliría",
      "ENGLISH": "I would carry out"
    },
    "TU": {
      "SPANISH": "Cumplirías",
      "ENGLISH": "You would carry out"
    },
    "EL": {
      "SPANISH": "Cumpliría",
      "ENGLISH": "He would carry out"
    },
    "ELLOS": {
      "SPANISH": "Cumplirían",
      "ENGLISH": "They would carry out"
    },
    "NOSOTROS": {
      "SPANISH": "Cumpliríamos",
      "ENGLISH": "We would carry out"
    },
    "VOSOTROS": {
      "SPANISH": "Cumpliríais",
      "ENGLISH": "You would carry out"
    }
  },
  "CONDICIONAL_COMPUESTO": {
    "YO": {
      "SPANISH": "Habría cumplido",
      "ENGLISH": "I would have carried out"
    },
    "TU": {
      "SPANISH": "Habrías cumplido",
      "ENGLISH": "You would have carried out"
    },
    "EL": {
      "SPANISH": "Habría cumplido",
      "ENGLISH": "He would have carried out"
    },
    "ELLOS": {
      "SPANISH": "Habrían cumplido",
      "ENGLISH": "They would have carried out"
    },
    "NOSOTROS": {
      "SPANISH": "Habríamos cumplido",
      "ENGLISH": "We would have carried out"
    },
    "VOSOTROS": {
      "SPANISH": "Habríais cumplido",
      "ENGLISH": "You would have carried out"
    }
  }
}
