{
  "PRESENTE": {
    "YO": {
      "SPANISH": "Dibujo",
      "ENGLISH": "I draw"
    },
    "TU": {
      "SPANISH": "Dibujas",
      "ENGLISH": "You draw"
    },
    "EL": {
      "SPANISH": "Dibuja",
      "ENGLISH": "He draws"
    },
    "ELLOS": {
      "SPANISH": "Dibujan",
      "ENGLISH": "They draw"
    },
    "NOSOTROS": {
      "SPANISH": "Dibujamos",
      "ENGLISH": "We draw"
    },
    "VOSOTROS": {
      "SPANISH": "Dibujáis",
      "ENGLISH": "You draw"
    }
  },
  "PERFECTO_COMPUESTO": {
    "YO": {
      "SPANISH": "He dibujado",
      "ENGLISH": "I have drawn"
    },
    "TU": {
      "SPANISH": "Has dibujado",
      "ENGLISH": "You have drawn"
    },
    "EL": {
      "SPANISH": "Ha dibujado",
      "ENGLISH": "He has drawn"
    },
    "ELLOS": {
      "SPANISH": "Han dibujado",
      "ENGLISH": "They have drawn"
    },
    "NOSOTROS": {
      "SPANISH": "Hemos dibujado",
      "ENGLISH": "We have drawn"
    },
    "VOSOTROS": {
      "SPANISH": "Habéis dibujado",
      "ENGLISH": "You have drawn"
    }
  },
  "PRETERITO_INDEFINIDO": {
    "YO": {
      "SPANISH": "Dibujé",
      "ENGLISH": "I drew"
    },
    "TU": {
      "SPANISH": "Dibujaste",
      "ENGLISH": "You drew"
    },
    "EL": {
      "SPANISH": "Dibujó",
      "ENGLISH": "He drew"
    },
    "ELLOS": {
      "SPANISH": "Dibujaron",
      "ENGLISH": "They drew"
    },
    "NOSOTROS": {
      "SPANISH": "Dibujamos",
      "ENGLISH": "We drew"
    },
    "VOSOTROS": {
      "SPANISH": "Dibujasteis",
      "ENGLISH": "You drew"
    }
  },
  "PRETERITO_PLUSCUAMPERFECTO": {
    "YO": {
      "SPANISH": "Había dibujado",
      "ENGLISH": "I had drawn"
    },
    "TU": {
      "SPANISH": "Habías dibujado",
      "ENGLISH": "You had drawn"
    },
    "EL": {
      "SPANISH": "Había dibujado",
      "ENGLISH": "He had drawn"
    },
    "ELLOS": {
      "SPANISH": "Habían dibujado",
      "ENGLISH": "They had drawn"
    },
    "NOSOTROS": {
      "SPANISH": "Habíamos dibujado",
      "ENGLISH": "We had drawn"
    },
    "VOSOTROS": {
      "SPANISH": "Habíais dibujado",
      "ENGLISH": "You had drawn"
    }
  },
  "PRETERITO_IMPERFECTO": {
    "YO": {
      "SPANISH": "Dibujé",
      "ENGLISH": "I drew"
    },
    "TU": {
      "SPANISH": "Dibujaste",
      "ENGLISH": "You drew"
    },
    "EL": {
      "SPANISH": "Dibujó",
      "ENGLISH": "He drew"
    },
    "ELLOS": {
      "SPANISH": "Dibujaron",
      "ENGLISH": "They drew"
    },
    "NOSOTROS": {
      "SPANISH": "Dibujamos",
      "ENGLISH": "We drew"
    },
    "VOSOTROS": {
      "SPANISH": "Dibujasteis",
      "ENGLISH": "You drew"
    }
  },
  "FUTURO_SIMPLE": {
    "YO": {
      "SPANISH": "Dibujaré",
      "ENGLISH": "I will draw"
    },
    "TU": {
      "SPANISH": "Dibujarás",
      "ENGLISH": "You will draw"
    },
    "EL": {
      "SPANISH": "Dibujará",
      "ENGLISH": "He will draw"
    },
    "ELLOS": {
      "SPANISH": "Dibujarán",
      "ENGLISH": "They will draw"
    },
    "NOSOTROS": {
      "SPANISH": "Dibujaremos",
      "ENGLISH": "We will draw"
    },
    "VOSOTROS": {
      "SPANISH": "Dibujaréis",
      "ENGLISH": "You will draw"
    }
  },
  "FUTURO_COMPUESTO": {
    "YO": {
      "SPANISH": "Habré dibujado",
      "ENGLISH": "I will have drawn"
    },
    "TU": {
      "SPANISH": "Habrás dibujado",
      "ENGLISH": "You will have drawn"
    },
    "EL": {
      "SPANISH": "Habrá dibujado",
      "ENGLISH": "He will have drawn"
    },
    "ELLOS": {
      "SPANISH": "Habrán dibujado",
      "ENGLISH": "They will have drawn"
    },
    "NOSOTROS": {
      "SPANISH": "Habremos dibujado",
      "ENGLISH": "We will have drawn"
    },
    "VOSOTROS": {
      "SPANISH": "Habréis dibujado",
      "ENGLISH": "You will have drawn"
    }
  },
  "CONDICIONAL_SIMPLE": {
    "YO": {
      "SPANISH": "Dibujaría",
      "ENGLISH": "I would draw"
    },
    "TU": {
      "SPANISH": "Dibujarías",
      "ENGLISH": "You would draw"
    },
    "EL": {
      "SPANISH": "Dibujaría",
      "ENGLISH": "He would draw"
    },
    "ELLOS": {
      "SPANISH": "Dibujarían",
      "ENGLISH": "They would draw"
    },
    "NOSOTROS": {
      "SPANISH": "Dibujaríamos",
      "ENGLISH": "We would draw"
    },
    "VOSOTROS": {
      "SPANISH": "Dibujaríais",
      "ENGLISH": "You would draw"
    }
  },
  "CONDICIONAL_COMPUESTO": {
    "YO": {
      "SPANISH": "Habría dibujado",
      "ENGLISH": "I would have drawn"
    },
    "TU": {
      "SPANISH": "Habrías dibujado",
      "ENGLISH": "You would have drawn"
    },
    "EL": {
      "SPANISH": "Habría dibujado",
      "ENGLISH": "He would have drawn"
    },
    "ELLOS": {
      "SPANISH": "Habrían dibujado",
      "ENGLISH": "They would have drawn"
    },
    "NOSOTROS": {
      "SPANISH": "Habríamos dibujado",
      "ENGLISH": "We would have drawn"
    },
    "VOSOTROS": {
      "SPANISH": "Habríais dibujado",
      "ENGLISH": "You would have drawn"
    }
  }
}
