{
  "PRESENTE": {
    "YO": {
      "SPANISH": "Divido",
      "ENGLISH": "I divide"
    },
    "TU": {
      "SPANISH": "Divides",
      "ENGLISH": "You divide"
    },
    "EL": {
      "SPANISH": "Divide",
      "ENGLISH": "He divides"
    },
    "ELLOS": {
      "SPANISH": "Dividen",
      "ENGLISH": "They divide"
    },
    "NOSOTROS": {
      "SPANISH": "Dividimos",
      "ENGLISH": "We divide"
    },
    "VOSOTROS": {
      "SPANISH": "Dividís",
      "ENGLISH": "You divide"
    }
  },
  "PERFECTO_COMPUESTO": {
    "YO": {
      "SPANISH": "He dividido",
      "ENGLISH": "I have divided"
    },
    "TU": {
      "SPANISH": "Has dividido",
      "ENGLISH": "You have divided"
    },
    "EL": {
      "SPANISH": "Ha dividido",
      "ENGLISH": "He has divided"
    },
    "ELLOS": {
      "SPANISH": "Han dividido",
      "ENGLISH": "They have divided"
    },
    "NOSOTROS": {
      "SPANISH": "Hemos dividido",
      "ENGLISH": "We have divided"
    },
    "VOSOTROS": {
      "SPANISH": "Habéis dividido",
      "ENGLISH": "You have divided"
    }
  },
  "PRETERITO_INDEFINIDO": {
    "YO": {
      "SPANISH": "Dividí",
      "ENGLISH": "I divided"
    },
    "TU": {
      "SPANISH": "Dividiste",
      "ENGLISH": "You divided"
    },
    "EL": {
      "SPANISH": "Dividió",
      "ENGLISH": "He divided"
    },
    "ELLOS": {
      "SPANISH": "Dividieron",
      "ENGLISH": "They divided"
    },
    "NOSOTROS": {
      "SPANISH": "Dividimos",
      "ENGLISH": "We divided"
    },
    "VOSOTROS": {
      "SPANISH": "Dividisteis",
      "ENGLISH": "You divided"
    }
  },
  "PRETERITO_PLUSCUAMPERFECTO": {
    "YO": {
      "SPANISH": "Había dividido",
      "ENGLISH": "I had divided"
    },
    "TU": {
      "SPANISH": "Habías dividido",
      "ENGLISH": "You had divided"
    },
    "EL": {
      "SPANISH": "Había dividido",
      "ENGLISH": "He had divided"
    },
    "ELLOS": {
      "SPANISH": "Habían dividido",
      "ENGLISH": "They had divided"
    },
    "NOSOTROS": {
      "SPANISH": "Habíamos dividido",
      "ENGLISH": "We had divided"
    },
    "VOSOTROS": {
      "SPANISH": "Habíais dividido",
      "ENGLISH": "You had divided"
    }
  },
  "PRETERITO_IMPERFECTO": {
    "YO": {
      "SPANISH": "Dividí",
      "ENGLISH": "I divided"
    },
    "TU": {
      "SPANISH": "Dividiste",
      "ENGLISH": "You divided"
    },
    "EL": {
      "SPANISH": "Dividió",
      "ENGLISH": "He divided"
    },
    "ELLOS": {
      "SPANISH": "Dividieron",
      "ENGLISH": "They divided"
    },
    "NOSOTROS": {
      "SPANISH": "Dividimos",
      "ENGLISH": "We divided"
    },
    "VOSOTROS": {
      "SPANISH": "Dividisteis",
      "ENGLISH": "You divided"
    }
  },
  "FUTURO_SIMPLE": {
    "YO": {
      "SPANISH": "Dividiré",
      "ENGLISH": "I will divide"
    },
    "TU": {
      "SPANISH": "Dividirás",
      "ENGLISH": "You will divide"
    },
    "EL": {
      "SPANISH": "Dividirá",
      "ENGLISH": "He will divide"
    },
    "ELLOS": {
      "SPANISH": "Dividirán",
      "ENGLISH": "They will divide"
    },
    "NOSOTROS": {
      "SPANISH": "Dividiremos",
      "ENGLISH": "We will divide"
    },
    "VOSOTROS": {
      "SPANISH": "Dividiréis",
      "ENGLISH": "You will divide"
    }
  },
  "FUTURO_COMPUESTO": {
    "YO": {
      "SPANISH": "Habré dividido",
      "ENGLISH": "I will have divided"
    },
    "TU": {
      "SPANISH": "Habrás dividido",
      "ENGLISH": "You will have divided"
    },
    "EL": {
      "SPANISH": "Habrá dividido",
      "ENGLISH": "He will have divided"
    },
    "ELLOS": {
      "SPANISH": "Habrán dividido",
      "ENGLISH": "They will have divided"
    },
    "NOSOTROS": {
      "SPANISH": "Habremos dividido",
      "ENGLISH": "We will have divided"
    },
    "VOSOTROS": {
      "SPANISH": "Habréis dividido",
      "ENGLISH": "You will have divided"
    }
  },
  "CONDICIONAL_SIMPLE": {
    "YO": {
      "SPANISH": "Dividiría",
      "ENGLISH": "I would divide"
    },
    "TU": {
      "SPANISH": "Dividirías",
      "ENGLISH": "You would divide"
    },
    "EL": {
      "SPANISH": "Dividiría",
      "ENGLISH": "He would divide"
    },
    "ELLOS": {
      "SPANISH": "Dividirían",
      "ENGLISH": "They would divide"
    },
    "NOSOTROS": {
      "SPANISH": "Dividiríamos",
      "ENGLISH": "We would divide"
    },
    "VOSOTROS": {
      "SPANISH": "Dividiríais",
      "ENGLISH": "You would divide"
    }
  },
  "CONDICIONAL_COMPUESTO": {
    "YO": {
      "SPANISH": "Habría dividido",
      "ENGLISH": "I would have divided"
    },
    "TU": {
      "SPANISH": "Habrías dividido",
      "ENGLISH": "You would have divided"
    },
    "EL": {
      "SPANISH": "Habría dividido",
      "ENGLISH": "He would have divided"
    },
    "ELLOS": {
      "SPANISH": "Habrían dividido",
      "ENGLISH": "They would have divided"
    },
    "NOSOTROS": {
      "SPANISH": "Habríamos dividido",
      "ENGLISH": "We would have divided"
    },
    "VOSOTROS": {
      "SPANISH": "Habríais dividido",
      "ENGLISH": "You would have divided"
    }
  }
}
