{
  "PRESENTE": {
    "YO": {
      "SPANISH": "Evacuo",
      "ENGLISH": "I evacuate"
    },
    "TU": {
      "SPANISH": "Evacuas",
      "ENGLISH": "You evacuate"
    },
    "EL": {
      "SPANISH": "Evacua",
      "ENGLISH": "He evacuates"
    },
    "ELLOS": {
      "SPANISH": "Evacuan",
      "ENGLISH": "They evacuate"
    },
    "NOSOTROS": {
      "SPANISH": "Evacuamos",
      "ENGLISH": "We evacuate"
    },
    "VOSOTROS": {
      "SPANISH": "Evacuáis",
      "ENGLISH": "You evacuate"
    }
  },
  "PERFECTO_COMPUESTO": {
    "YO": {
      "SPANISH": "He evacuado",
      "ENGLISH": "I have evacuated"
    },
    "TU": {
      "SPANISH": "Has evacuado",
      "ENGLISH": "You have evacuated"
    },
    "EL": {
      "SPANISH": "Ha evacuado",
      "ENGLISH": "He has evacuated"
    },
    "ELLOS": {
      "SPANISH": "Han evacuado",
      "ENGLISH": "They have evacuated"
    },
    "NOSOTROS": {
      "SPANISH": "Hemos evacuado",
      "ENGLISH": "We have evacuated"
    },
    "VOSOTROS": {
      "SPANISH": "Habéis evacuado",
      "ENGLISH": "You have evacuated"
    }
  },
  "PRETERITO_INDEFINIDO": {
    "YO": {
      "SPANISH": "Evacué",
      "ENGLISH": "I evacuated"
    },
    "TU": {
      "SPANISH": "Evacuaste",
      "ENGLISH": "You evacuated"
    },
    "EL": {
      "SPANISH": "Evacuó",
      "ENGLISH": "He evacuated"
    },
    "ELLOS": {
      "SPANISH": "Evacuaron",
      "ENGLISH": "They evacuated"
    },
    "NOSOTROS": {
      "SPANISH": "Evacuamos",
      "ENGLISH": "We evacuated"
    },
    "VOSOTROS": {
      "SPANISH": "Evacuasteis",
      "ENGLISH": "You evacuated"
    }
  },
  "PRETERITO_PLUSCUAMPERFECTO": {
    "YO": {
      "SPANISH": "Había evacuado",
      "ENGLISH": "I had evacuated"
    },
    "TU": {
      "SPANISH": "Habías evacuado",
      "ENGLISH": "You had evacuated"
    },
    "EL": {
      "SPANISH": "Había evacuado",
      "ENGLISH": "He had evacuated"
    },
    "ELLOS": {
      "SPANISH": "Habían evacuado",
      "ENGLISH": "They had evacuated"
    },
    "NOSOTROS": {
      "SPANISH": "Habíamos evacuado",
      "ENGLISH": "We had evacuated"
    },
    "VOSOTROS": {
      "SPANISH": "Habíais evacuado",
      "ENGLISH": "You had evacuated"
    }
  },
  "PRETERITO_IMPERFECTO": {
    "YO": {
      "SPANISH": "Evacué",
      "ENGLISH": "I evacuated"
    },
    "TU": {
      "SPANISH": "Evacuaste",
      "ENGLISH": "You evacuated"
    },
    "EL": {
      "SPANISH": "Evacuó",
      "ENGLISH": "He evacuated"
    },
    "ELLOS": {
      "SPANISH": "Evacuaron",
      "ENGLISH": "They evacuated"
    },
    "NOSOTROS": {
      "SPANISH": "Evacuamos",
      "ENGLISH": "We evacuated"
    },
    "VOSOTROS": {
      "SPANISH": "Evacuasteis",
      "ENGLISH": "You evacuated"
    }
  },
  "FUTURO_SIMPLE": {
    "YO": {
      "SPANISH": "Evacuaré",
      "ENGLISH": "I will evacuate"
    },
    "TU": {
      "SPANISH": "Evacuarás",
      "ENGLISH": "You will evacuate"
    },
    "EL": {
      "SPANISH": "Evacuará",
      "ENGLISH": "He will evacuate"
    },
    "ELLOS": {
      "SPANISH": "Evacuarán",
      "ENGLISH": "They will evacuate"
    },
    "NOSOTROS": {
      "SPANISH": "Evacuaremos",
      "ENGLISH": "We will evacuate"
    },
    "VOSOTROS": {
      "SPANISH": "Evacuaréis",
      "ENGLISH": "You will evacuate"
    }
  },
  "FUTURO_COMPUESTO": {
    "YO": {
      "SPANISH": "Habré evacuado",
      "ENGLISH": "I will have evacuated"
    },
    "TU": {
      "SPANISH": "Habrás evacuado",
      "ENGLISH": "You will have evacuated"
    },
    "EL": {
      "SPANISH": "Habrá evacuado",
      "ENGLISH": "He will have evacuated"
    },
    "ELLOS": {
      "SPANISH": "Habrán evacuado",
      "ENGLISH": "They will have evacuated"
    },
    "NOSOTROS": {
      "SPANISH": "Habremos evacuado",
      "ENGLISH": "We will have evacuated"
    },
    "VOSOTROS": {
      "SPANISH": "Habréis evacuado",
      "ENGLISH": "You will have evacuated"
    }
  },
  "CONDICIONAL_SIMPLE": {
    "YO": {
      "SPANISH": "Evacuaría",
      "ENGLISH": "I would evacuate"
    },
    "TU": {
      "SPANISH": "Evacuarías",
      "ENGLISH": "You would evacuate"
    },
    "EL": {
      "SPANISH": "Evacuaría",
      "ENGLISH": "He would evacuate"
    },
    "ELLOS": {
      "SPANISH": "Evacuarían",
      "ENGLISH": "They would evacuate"
    },
    "NOSOTROS": {
      "SPANISH": "Evacuaríamos",
      "ENGLISH": "We would evacuate"
    },
    "VOSOTROS": {
      "SPANISH": "Evacuaríais",
      "ENGLISH": "You would evacuate"
    }
  },
  "CONDICIONAL_COMPUESTO": {
    "YO": {
      "SPANISH": "Habría evacuado",
      "ENGLISH": "I would have evacuated"
    },
    "TU": {
      "SPANISH": "Habrías evacuado",
      "ENGLISH": "You would have evacuated"
    },
    "EL": {
      "SPANISH": "Habría evacuado",
      "ENGLISH": "He would have evacuated"
    },
    "ELLOS": {
      "SPANISH": "Habrían evacuado",
      "ENGLISH": "They would have evacuated"
    },
    "NOSOTROS": {
      "SPANISH": "Habríamos evacuado",
      "ENGLISH": "We would have evacuated"
    },
    "VOSOTROS": {
      "SPANISH": "Habríais evacuado",
      "ENGLISH": "You would have evacuated"
    }
  }
}
