{
  "PRESENT_SIMPLE": {
    "YO": {
      "SPANISH": "Imprimo",
      "ENGLISH": "I print"
    },
    "TU": {
      "SPANISH": "Imprimes",
      "ENGLISH": "You print"
    },
    "EL": {
      "SPANISH": "Imprime",
      "ENGLISH": "He prints"
    },
    "ELLOS": {
      "SPANISH": "Imprimen",
      "ENGLISH": "They print"
    },
    "NOSOTROS": {
      "SPANISH": "Imprimimos",
      "ENGLISH": "We print"
    },
    "VOSOTROS": {
      "SPANISH": "Imprimís",
      "ENGLISH": "You print"
    }
  },
  "PRESENT_PERFECT": {
    "YO": {
      "SPANISH": "He imprimido",
      "ENGLISH": "I have printed"
    },
    "TU": {
      "SPANISH": "Has imprimido",
      "ENGLISH": "You have printed"
    },
    "EL": {
      "SPANISH": "Ha imprimido",
      "ENGLISH": "He has printed"
    },
    "ELLOS": {
      "SPANISH": "Han imprimido",
      "ENGLISH": "They have printed"
    },
    "NOSOTROS": {
      "SPANISH": "Hemos imprimido",
      "ENGLISH": "We have printed"
    },
    "VOSOTROS": {
      "SPANISH": "Habéis imprimido",
      "ENGLISH": "You have printed"
    }
  },
  "PAST_SIMPLE": {
    "YO": {
      "SPANISH": "Imprimí",
      "ENGLISH": "I printed"
    },
    "TU": {
      "SPANISH": "Imprimiste",
      "ENGLISH": "You printed"
    },
    "EL": {
      "SPANISH": "Imprimió",
      "ENGLISH": "He printed"
    },
    "ELLOS": {
      "SPANISH": "Imprimieron",
      "ENGLISH": "They printed"
    },
    "NOSOTROS": {
      "SPANISH": "Imprimimos",
      "ENGLISH": "We printed"
    },
    "VOSOTROS": {
      "SPANISH": "Imprimisteis",
      "ENGLISH": "You printed"
    }
  },
  "PAST_PERFECT": {
    "YO": {
      "SPANISH": "Había imprimido",
      "ENGLISH": "I had printed"
    },
    "TU": {
      "SPANISH": "Habías imprimido",
      "ENGLISH": "You had printed"
    },
    "EL": {
      "SPANISH": "Había imprimido",
      "ENGLISH": "He had printed"
    },
    "ELLOS": {
      "SPANISH": "Habían imprimido",
      "ENGLISH": "They had printed"
    },
    "NOSOTROS": {
      "SPANISH": "Habíamos imprimido",
      "ENGLISH": "We had printed"
    },
    "VOSOTROS": {
      "SPANISH": "Habíais imprimido",
      "ENGLISH": "You had printed"
    }
  },
  "PRETERITO_IMPERFECTO": {
    "YO": {
      "SPANISH": "Imprimí",
      "ENGLISH": "I printed"
    },
    "TU": {
      "SPANISH": "Imprimiste",
      "ENGLISH": "You printed"
    },
    "EL": {
      "SPANISH": "Imprimió",
      "ENGLISH": "He printed"
    },
    "ELLOS": {
      "SPANISH": "Imprimieron",
      "ENGLISH": "They printed"
    },
    "NOSOTROS": {
      "SPANISH": "Imprimimos",
      "ENGLISH": "We printed"
    },
    "VOSOTROS": {
      "SPANISH": "Imprimisteis",
      "ENGLISH": "You printed"
    }
  },
  "FUTURE_SIMPLE": {
    "YO": {
      "SPANISH": "Imprimiré",
      "ENGLISH": "I will print"
    },
    "TU": {
      "SPANISH": "Imprimirás",
      "ENGLISH": "You will print"
    },
    "EL": {
      "SPANISH": "Imprimirá",
      "ENGLISH": "He will print"
    },
    "ELLOS": {
      "SPANISH": "Imprimirán",
      "ENGLISH": "They will print"
    },
    "NOSOTROS": {
      "SPANISH": "Imprimiremos",
      "ENGLISH": "We will print"
    },
    "VOSOTROS": {
      "SPANISH": "Imprimiréis",
      "ENGLISH": "You will print"
    }
  },
  "FUTURO_COMPUESTO": {
    "YO": {
      "SPANISH": "Habré imprimido",
      "ENGLISH": "I will have printed"
    },
    "TU": {
      "SPANISH": "Habrás imprimido",
      "ENGLISH": "You will have printed"
    },
    "EL": {
      "SPANISH": "Habrá imprimido",
      "ENGLISH": "He will have printed"
    },
    "ELLOS": {
      "SPANISH": "Habrán imprimido",
      "ENGLISH": "They will have printed"
    },
    "NOSOTROS": {
      "SPANISH": "Habremos imprimido",
      "ENGLISH": "We will have printed"
    },
    "VOSOTROS": {
      "SPANISH": "Habréis imprimido",
      "ENGLISH": "You will have printed"
    }
  },
  "CONDICIONAL_SIMPLE": {
    "YO": {
      "SPANISH": "Imprimiría",
      "ENGLISH": "I would print"
    },
    "TU": {
      "SPANISH": "Imprimirías",
      "ENGLISH": "You would print"
    },
    "EL": {
      "SPANISH": "Imprimiría",
      "ENGLISH": "He would print"
    },
    "ELLOS": {
      "SPANISH": "Imprimirían",
      "ENGLISH": "They would print"
    },
    "NOSOTROS": {
      "SPANISH": "Imprimiríamos",
      "ENGLISH": "We would print"
    },
    "VOSOTROS": {
      "SPANISH": "Imprimiríais",
      "ENGLISH": "You would print"
    }
  },
  "CONDICIONAL_COMPUESTO": {
    "YO": {
      "SPANISH": "Habría imprimido",
      "ENGLISH": "I would have printed"
    },
    "TU": {
      "SPANISH": "Habrías imprimido",
      "ENGLISH": "You would have printed"
    },
    "EL": {
      "SPANISH": "Habría imprimido",
      "ENGLISH": "He would have printed"
    },
    "ELLOS": {
      "SPANISH": "Habrían imprimido",
      "ENGLISH": "They would have printed"
    },
    "NOSOTROS": {
      "SPANISH": "Habríamos imprimido",
      "ENGLISH": "We would have printed"
    },
    "VOSOTROS": {
      "SPANISH": "Habríais imprimido",
      "ENGLISH": "You would have printed"
    }
  }
}
