{
  "PRESENT_SIMPLE": {
    "YO": {
      "SPANISH": "Huelo ",
      "ENGLISH": "I smell"
    },
    "TU": {
      "SPANISH": "Hueles ",
      "ENGLISH": "You smell"
    },
    "EL": {
      "SPANISH": "Huele ",
      "ENGLISH": "He smells"
    },
    "ELLOS": {
      "SPANISH": "Huelen ",
      "ENGLISH": "They smell"
    },
    "NOSOTROS": {
      "SPANISH": "Olemos",
      "ENGLISH": "We smell"
    },
    "VOSOTROS": {
      "SPANISH": "Oléis",
      "ENGLISH": "You smell"
    }
  },
  "PRESENT_PERFECT": {
    "YO": {
      "SPANISH": "He olido",
      "ENGLISH": "I have smelled"
    },
    "TU": {
      "SPANISH": "Has olido",
      "ENGLISH": "You have smelled"
    },
    "EL": {
      "SPANISH": "Ha olido",
      "ENGLISH": "He has smelled"
    },
    "ELLOS": {
      "SPANISH": "Han olido",
      "ENGLISH": "They have smelled"
    },
    "NOSOTROS": {
      "SPANISH": "Hemos olido",
      "ENGLISH": "We have smelled"
    },
    "VOSOTROS": {
      "SPANISH": "Habéis olido",
      "ENGLISH": "You have smelled"
    }
  },
  "PAST_SIMPLE": {
    "YO": {
      "SPANISH": "Olí",
      "ENGLISH": "I smelled"
    },
    "TU": {
      "SPANISH": "Oliste",
      "ENGLISH": "You smelled"
    },
    "EL": {
      "SPANISH": "Olió",
      "ENGLISH": "He smelled"
    },
    "ELLOS": {
      "SPANISH": "Olieron",
      "ENGLISH": "They smelled"
    },
    "NOSOTROS": {
      "SPANISH": "Olimos",
      "ENGLISH": "We smelled"
    },
    "VOSOTROS": {
      "SPANISH": "Olisteis",
      "ENGLISH": "You smelled"
    }
  },
  "PAST_PERFECT": {
    "YO": {
      "SPANISH": "Había olido",
      "ENGLISH": "I had smelled"
    },
    "TU": {
      "SPANISH": "Habías olido",
      "ENGLISH": "You had smelled"
    },
    "EL": {
      "SPANISH": "Había olido",
      "ENGLISH": "He had smelled"
    },
    "ELLOS": {
      "SPANISH": "Habían olido",
      "ENGLISH": "They had smelled"
    },
    "NOSOTROS": {
      "SPANISH": "Habíamos olido",
      "ENGLISH": "We had smelled"
    },
    "VOSOTROS": {
      "SPANISH": "Habíais olido",
      "ENGLISH": "You had smelled"
    }
  },
  "PRETERITO_IMPERFECTO": {
    "YO": {
      "SPANISH": "Olí",
      "ENGLISH": "I smelled"
    },
    "TU": {
      "SPANISH": "Oliste",
      "ENGLISH": "You smelled"
    },
    "EL": {
      "SPANISH": "Olió",
      "ENGLISH": "He smelled"
    },
    "ELLOS": {
      "SPANISH": "Olieron",
      "ENGLISH": "They smelled"
    },
    "NOSOTROS": {
      "SPANISH": "Olimos",
      "ENGLISH": "We smelled"
    },
    "VOSOTROS": {
      "SPANISH": "Olisteis",
      "ENGLISH": "You smelled"
    }
  },
  "FUTURE_SIMPLE": {
    "YO": {
      "SPANISH": "Oleré",
      "ENGLISH": "I will smell"
    },
    "TU": {
      "SPANISH": "Olerás",
      "ENGLISH": "You will smell"
    },
    "EL": {
      "SPANISH": "Olerá",
      "ENGLISH": "He will smell"
    },
    "ELLOS": {
      "SPANISH": "Olerán",
      "ENGLISH": "They will smell"
    },
    "NOSOTROS": {
      "SPANISH": "Oleremos",
      "ENGLISH": "We will smell"
    },
    "VOSOTROS": {
      "SPANISH": "Oleréis",
      "ENGLISH": "You will smell"
    }
  },
  "FUTURO_COMPUESTO": {
    "YO": {
      "SPANISH": "Habré olido",
      "ENGLISH": "I will have smelled"
    },
    "TU": {
      "SPANISH": "Habrás olido",
      "ENGLISH": "You will have smelled"
    },
    "EL": {
      "SPANISH": "Habrá olido",
      "ENGLISH": "He will have smelled"
    },
    "ELLOS": {
      "SPANISH": "Habrán olido",
      "ENGLISH": "They will have smelled"
    },
    "NOSOTROS": {
      "SPANISH": "Habremos olido",
      "ENGLISH": "We will have smelled"
    },
    "VOSOTROS": {
      "SPANISH": "Habréis olido",
      "ENGLISH": "You will have smelled"
    }
  },
  "CONDICIONAL_SIMPLE": {
    "YO": {
      "SPANISH": "Olería",
      "ENGLISH": "I would smell"
    },
    "TU": {
      "SPANISH": "Olerías",
      "ENGLISH": "You would smell"
    },
    "EL": {
      "SPANISH": "Olería",
      "ENGLISH": "He would smell"
    },
    "ELLOS": {
      "SPANISH": "Olerían",
      "ENGLISH": "They would smell"
    },
    "NOSOTROS": {
      "SPANISH": "Oleríamos",
      "ENGLISH": "We would smell"
    },
    "VOSOTROS": {
      "SPANISH": "Oleríais",
      "ENGLISH": "You would smell"
    }
  },
  "CONDICIONAL_COMPUESTO": {
    "YO": {
      "SPANISH": "Habría olido",
      "ENGLISH": "I would have smelled"
    },
    "TU": {
      "SPANISH": "Habrías olido",
      "ENGLISH": "You would have smelled"
    },
    "EL": {
      "SPANISH": "Habría olido",
      "ENGLISH": "He would have smelled"
    },
    "ELLOS": {
      "SPANISH": "Habrían olido",
      "ENGLISH": "They would have smelled"
    },
    "NOSOTROS": {
      "SPANISH": "Habríamos olido",
      "ENGLISH": "We would have smelled"
    },
    "VOSOTROS": {
      "SPANISH": "Habríais olido",
      "ENGLISH": "You would have smelled"
    }
  }
}
