{
  "PRESENT_SIMPLE": {
    "YO": {
      "SPANISH": "Suelo ",
      "ENGLISH": "I am used to"
    },
    "TU": {
      "SPANISH": "Sueles ",
      "ENGLISH": "You are used to"
    },
    "EL": {
      "SPANISH": "Suele ",
      "ENGLISH": "He is used to"
    },
    "ELLOS": {
      "SPANISH": "Suelen ",
      "ENGLISH": "They are used to"
    },
    "NOSOTROS": {
      "SPANISH": "Solemos",
      "ENGLISH": "We are used to"
    },
    "VOSOTROS": {
      "SPANISH": "Soléis",
      "ENGLISH": "You are used to"
    }
  },
  "PRESENT_PERFECT": {
    "YO": {
      "SPANISH": "He solido",
      "ENGLISH": "I have been used to"
    },
    "TU": {
      "SPANISH": "Has solido",
      "ENGLISH": "You have been used to"
    },
    "EL": {
      "SPANISH": "Ha solido",
      "ENGLISH": "He has been used to"
    },
    "ELLOS": {
      "SPANISH": "Han solido",
      "ENGLISH": "They have been used to"
    },
    "NOSOTROS": {
      "SPANISH": "Hemos solido",
      "ENGLISH": "We have been used to"
    },
    "VOSOTROS": {
      "SPANISH": "Habéis solido",
      "ENGLISH": "You have been used to"
    }
  },
  "PAST_SIMPLE": {
    "YO": {
      "SPANISH": "Solí",
      "ENGLISH": "I was used to"
    },
    "TU": {
      "SPANISH": "Soliste",
      "ENGLISH": "You were used to"
    },
    "EL": {
      "SPANISH": "Solió",
      "ENGLISH": "He was used to"
    },
    "ELLOS": {
      "SPANISH": "Solieron",
      "ENGLISH": "They were used to"
    },
    "NOSOTROS": {
      "SPANISH": "Solimos",
      "ENGLISH": "We were used to"
    },
    "VOSOTROS": {
      "SPANISH": "Solisteis",
      "ENGLISH": "You were used to"
    }
  },
  "PAST_PERFECT": {
    "YO": {
      "SPANISH": "Había solido",
      "ENGLISH": "I had been used to"
    },
    "TU": {
      "SPANISH": "Habías solido",
      "ENGLISH": "You had been used to"
    },
    "EL": {
      "SPANISH": "Había solido",
      "ENGLISH": "He had been used to"
    },
    "ELLOS": {
      "SPANISH": "Habían solido",
      "ENGLISH": "They had been used to"
    },
    "NOSOTROS": {
      "SPANISH": "Habíamos solido",
      "ENGLISH": "We had been used to"
    },
    "VOSOTROS": {
      "SPANISH": "Habíais solido",
      "ENGLISH": "You had been used to"
    }
  },
  "PRETERITO_IMPERFECTO": {
    "YO": {
      "SPANISH": "Solí",
      "ENGLISH": "I was used to"
    },
    "TU": {
      "SPANISH": "Soliste",
      "ENGLISH": "You were used to"
    },
    "EL": {
      "SPANISH": "Solió",
      "ENGLISH": "He was used to"
    },
    "ELLOS": {
      "SPANISH": "Solieron",
      "ENGLISH": "They were used to"
    },
    "NOSOTROS": {
      "SPANISH": "Solimos",
      "ENGLISH": "We were used to"
    },
    "VOSOTROS": {
      "SPANISH": "Solisteis",
      "ENGLISH": "You were used to"
    }
  },
  "FUTURE_SIMPLE": {
    "YO": {
      "SPANISH": "Soleré",
      "ENGLISH": "I will be used to"
    },
    "TU": {
      "SPANISH": "Solerás",
      "ENGLISH": "You will be used to"
    },
    "EL": {
      "SPANISH": "Solerá",
      "ENGLISH": "He will be used to"
    },
    "ELLOS": {
      "SPANISH": "Solerán",
      "ENGLISH": "They will be used to"
    },
    "NOSOTROS": {
      "SPANISH": "Soleremos",
      "ENGLISH": "We will be used to"
    },
    "VOSOTROS": {
      "SPANISH": "Soleréis",
      "ENGLISH": "You will be used to"
    }
  },
  "FUTURO_COMPUESTO": {
    "YO": {
      "SPANISH": "Habré solido",
      "ENGLISH": "I will have been used to"
    },
    "TU": {
      "SPANISH": "Habrás solido",
      "ENGLISH": "You will have been used to"
    },
    "EL": {
      "SPANISH": "Habrá solido",
      "ENGLISH": "He will have been used to"
    },
    "ELLOS": {
      "SPANISH": "Habrán solido",
      "ENGLISH": "They will have been used to"
    },
    "NOSOTROS": {
      "SPANISH": "Habremos solido",
      "ENGLISH": "We will have been used to"
    },
    "VOSOTROS": {
      "SPANISH": "Habréis solido",
      "ENGLISH": "You will have been used to"
    }
  },
  "CONDICIONAL_SIMPLE": {
    "YO": {
      "SPANISH": "Solería",
      "ENGLISH": "I would be used to"
    },
    "TU": {
      "SPANISH": "Solerías",
      "ENGLISH": "You would be used to"
    },
    "EL": {
      "SPANISH": "Solería",
      "ENGLISH": "He would be used to"
    },
    "ELLOS": {
      "SPANISH": "Solerían",
      "ENGLISH": "They would be used to"
    },
    "NOSOTROS": {
      "SPANISH": "Soleríamos",
      "ENGLISH": "We would be used to"
    },
    "VOSOTROS": {
      "SPANISH": "Soleríais",
      "ENGLISH": "You would be used to"
    }
  },
  "CONDICIONAL_COMPUESTO": {
    "YO": {
      "SPANISH": "Habría solido",
      "ENGLISH": "I would have been used to"
    },
    "TU": {
      "SPANISH": "Habrías solido",
      "ENGLISH": "You would have been used to"
    },
    "EL": {
      "SPANISH": "Habría solido",
      "ENGLISH": "He would have been used to"
    },
    "ELLOS": {
      "SPANISH": "Habrían solido",
      "ENGLISH": "They would have been used to"
    },
    "NOSOTROS": {
      "SPANISH": "Habríamos solido",
      "ENGLISH": "We would have been used to"
    },
    "VOSOTROS": {
      "SPANISH": "Habríais solido",
      "ENGLISH": "You would have been used to"
    }
  }
}
